nonebot_plugin_imgsearch/__init__.py
nonebot_plugin_imgsearch/ascii2d.py
nonebot_plugin_imgsearch/config.py
nonebot_plugin_imgsearch/response.py
nonebot_plugin_imgsearch/saucenao.py
nonebot_plugin_imgsearch/utils.py
nonebot_plugin_imgsearch-0.1.2.dist-info/LICENSE
nonebot_plugin_imgsearch-0.1.2.dist-info/WHEEL
nonebot_plugin_imgsearch-0.1.2.dist-info/METADATA
nonebot_plugin_imgsearch-0.1.2.dist-info/RECORD
