Metadata-Version: 2.1
Name: nonebot-plugin-imgsearch
Version: 0.1.2
Summary: A image search plugin for nonebot2
Home-page: https://github.com/bakashigure/nonebot_plugin_imgsearch
License: MIT
Author: bakashigure
Author-email: bakashigure@hotmail.com
Requires-Python: >=3.7.3,<4.0.0
Classifier: License :: OSI Approved :: MIT License
Classifier: Operating System :: OS Independent
Classifier: Programming Language :: Python :: 3
Classifier: Programming Language :: Python :: 3.10
Classifier: Programming Language :: Python :: 3.7
Classifier: Programming Language :: Python :: 3.8
Classifier: Programming Language :: Python :: 3.9
Requires-Dist: beautifulsoup4 (>=4.9.1,<5.0.0)
Requires-Dist: httpx[http2] (>=0.20.0,<1.0.0)
Requires-Dist: loguru (>=0.5.1,<0.6.0)
Project-URL: Repository, https://github.com/bakashigure/nonebot_plugin_imgsearch
